uologging/__init__.py
uologging/cli.py
uologging/downloads.py
uologging/format.py
uologging/performance.py
uologging/uologging.py
uologging-0.9.1.dist-info/METADATA
uologging-0.9.1.dist-info/WHEEL
uologging-0.9.1.dist-info/top_level.txt
uologging-0.9.1.dist-info/RECORD
