Metadata-Version: 2.4
Name: uologging
Version: 0.9.1
Summary: Auto-Configuration solution for Python built-in logging.
Author-email: University of Oregon <nsdevops@uoregon.edu>
Keywords: NTS,UO
Classifier: Development Status :: 3 - Alpha
Classifier: Intended Audience :: Developers
Classifier: License :: OSI Approved :: MIT License
Classifier: Programming Language :: Python :: 3.6
Classifier: Programming Language :: Python :: 3.7
Classifier: Programming Language :: Python :: 3.8
Classifier: Programming Language :: Python :: 3.9
Classifier: Programming Language :: Python :: 3.10
Classifier: Programming Language :: Python :: 3.11
Classifier: Programming Language :: Python :: 3.12
Requires-Python: >=3.6
Provides-Extra: dev
Requires-Dist: pytest; extra == "dev"
Requires-Dist: assertpy; extra == "dev"
Provides-Extra: cicd
Requires-Dist: pytest; extra == "cicd"
Requires-Dist: pytest-cov; extra == "cicd"
Requires-Dist: assertpy; extra == "cicd"
Provides-Extra: optional
Requires-Dist: humanize; extra == "optional"
